pymdtools/__init__.py
pymdtools/_about.py
pymdtools/common.py
pymdtools/filetools.py
pymdtools/instruction.py
pymdtools/markdownify.py
pymdtools/mdcommon.py
pymdtools/mdfile.py
pymdtools/mdrender.py
pymdtools/mdtopdf.py
pymdtools/mistunege.py
pymdtools/normalize.py
pymdtools/translate.py
pymdtools/version.py
pymdtools/layouts/bootstrap3/page.html
pymdtools/layouts/bootstrap3/assets/css/bootstrap.min.css
pymdtools/layouts/bootstrap3/assets/css/hljs-github.min.css
pymdtools/layouts/bootstrap3/assets/css/pilcrow.css
pymdtools/layouts/bootstrap3/assets/fonts/glyphicons-halflings-regular.eot
pymdtools/layouts/bootstrap3/assets/fonts/glyphicons-halflings-regular.svg
pymdtools/layouts/bootstrap3/assets/fonts/glyphicons-halflings-regular.ttf
pymdtools/layouts/bootstrap3/assets/fonts/glyphicons-halflings-regular.woff
pymdtools/layouts/bootstrap3/assets/js/bootstrap.min.js
pymdtools/layouts/github/page.html
pymdtools/layouts/github/assets/css/github-markdown.css
pymdtools/layouts/github/assets/css/hljs-github.min.css
pymdtools/layouts/github/assets/css/pilcrow.css
pymdtools/layouts/jasonm23-dark/page.html
pymdtools/layouts/jasonm23-dark/assets/hljs-github.min.css
pymdtools/layouts/jasonm23-dark/assets/pilcrow.css
pymdtools/layouts/jasonm23-dark/assets/style.css
pymdtools/layouts/jasonm23-foghorn/page.html
pymdtools/layouts/jasonm23-foghorn/assets/hljs-github.min.css
pymdtools/layouts/jasonm23-foghorn/assets/pilcrow.css
pymdtools/layouts/jasonm23-foghorn/assets/style.css
pymdtools/layouts/jasonm23-markdown/page.html
pymdtools/layouts/jasonm23-markdown/assets/hljs-github.min.css
pymdtools/layouts/jasonm23-markdown/assets/pilcrow.css
pymdtools/layouts/jasonm23-markdown/assets/style.css
pymdtools/layouts/jasonm23-swiss/page.html
pymdtools/layouts/jasonm23-swiss/assets/hljs-github.min.css
pymdtools/layouts/jasonm23-swiss/assets/pilcrow.css
pymdtools/layouts/jasonm23-swiss/assets/style.css
pymdtools/layouts/markedapp-byword/page.html
pymdtools-1.0.21.dist-info/licenses/LICENSE.md
pymdtools-1.0.21.dist-info/METADATA
pymdtools-1.0.21.dist-info/WHEEL
pymdtools-1.0.21.dist-info/top_level.txt
pymdtools-1.0.21.dist-info/RECORD
