Metadata-Version: 2.4
Name: pymdtools
Version: 1.0.21
Summary: Markdown Tools developed for Guichet Entreprises
Home-page: https://github.com/IIXIXII/pymdtools
Author: Florent Tournois
Author-email: florent.tournois@gmail.fr
License: License :: OSI Approved :: MIT License
Classifier: Programming Language :: Python :: 3
Classifier: Operating System :: OS Independent
Classifier: License :: OSI Approved :: MIT License
Requires-Python: >=3.7
License-File: LICENSE.md
Requires-Dist: markdown
Requires-Dist: pdfkit
Requires-Dist: PyPDF2
Requires-Dist: python-dateutil
Dynamic: author
Dynamic: author-email
Dynamic: classifier
Dynamic: description
Dynamic: description-content-type
Dynamic: home-page
Dynamic: license
Dynamic: license-file
Dynamic: requires-dist
Dynamic: requires-python
Dynamic: summary
